[{
    "company": "Alfreds Futterkiste",
    "contact": "Maria Anders",
    "country": "Germany"
}, {
    "company": "Berglunds snabbköp",
    "contact": "Christina Berglund",
    "country": "Sweden"
}, {
    "company": "Centro comercial Moctezuma",
    "contact": "Francisco Chang",
    "country": "Mexico"
}, {
    "company": "Ernst Handel",
    "contact": "Roland Mendel",
    "country": "Austria"
}, {
    "company": "FISSA Fabrica Inter. Salchichas S.A.",
    "contact": "Diego Roel",
    "country": "Spain"
}, {
    "company": "Galería del gastrónomo",
    "contact": "Eduardo Saavedra",
    "country": "Spain"
}, {
    "company": "Island Trading",
    "contact": "Helen Bennett",
    "country": "UK"
}, {
    "company": "Königlich Essen",
    "contact": "Philip Cramer",
    "country": "Germany"
}, {
    "company": "Laughing Bacchus Wine Cellars",
    "contact": "Yoshi Tannamuri",
    "country": "Canada"
}, {
    "company": "Magazzini Alimentari Riuniti",
    "contact": "Giovanni Rovelli",
    "country": "Italy"
}, {
    "company": "North/South",
    "contact": "Simon Crowther",
    "country": "UK"
}, {
    "company": "Paris spécialités",
    "contact": "Marie Bertrand",
    "country": "France"
}, {
    "company": "Rattlesnake Canyon Grocery",
    "contact": "Paula Wilson",
    "country": "USA"
}, {
    "company": "Simons bistro",
    "contact": "Jytte Petersen",
    "country": "Denmark"
}, {
    "company": "The Big Cheese",
    "contact": "Liz Nixon",
    "country": "USA"
}, {
    "company": "Vaffeljernet",
    "contact": "Palle Ibsen",
    "country": "Denmark"
}, {
    "company": "Wolski Zajazd",
    "contact": "Zbyszek Piestrzeniewicz",
    "country": "Poland"
}, {
    "company": "Alfreds Futterkiste",
    "contact": "Maria Anders",
    "country": "Germany"
}, {
    "company": "Berglunds snabbköp",
    "contact": "Christina Berglund",
    "country": "Sweden"
}, {
    "company": "Centro comercial Moctezuma",
    "contact": "Francisco Chang",
    "country": "Mexico"
}, {
    "company": "Ernst Handel",
    "contact": "Roland Mendel",
    "country": "Austria"
}, {
    "company": "FISSA Fabrica Inter. Salchichas S.A.",
    "contact": "Diego Roel",
    "country": "Spain"
}, {
    "company": "Galería del gastrónomo",
    "contact": "Eduardo Saavedra",
    "country": "Spain"
}, {
    "company": "Island Trading",
    "contact": "Helen Bennett",
    "country": "UK"
}, {
    "company": "Königlich Essen",
    "contact": "Philip Cramer",
    "country": "Germany"
}, {
    "company": "Laughing Bacchus Wine Cellars",
    "contact": "Yoshi Tannamuri",
    "country": "Canada"
}, {
    "company": "Magazzini Alimentari Riuniti",
    "contact": "Giovanni Rovelli",
    "country": "Italy"
}, {
    "company": "North/South",
    "contact": "Simon Crowther",
    "country": "UK"
}, {
    "company": "Paris spécialités",
    "contact": "Marie Bertrand",
    "country": "France"
}, {
    "company": "Rattlesnake Canyon Grocery",
    "contact": "Paula Wilson",
    "country": "USA"
}, {
    "company": "Simons bistro",
    "contact": "Jytte Petersen",
    "country": "Denmark"
}, {
    "company": "The Big Cheese",
    "contact": "Liz Nixon",
    "country": "USA"
}, {
    "company": "Vaffeljernet",
    "contact": "Palle Ibsen",
    "country": "Denmark"
}, {
    "company": "Wolski Zajazd",
    "contact": "Zbyszek Piestrzeniewicz",
    "country": "Poland"
}, {
    "company": "Alfreds Futterkiste",
    "contact": "Maria Anders",
    "country": "Germany"
}, {
    "company": "Berglunds snabbköp",
    "contact": "Christina Berglund",
    "country": "Sweden"
}, {
    "company": "Centro comercial Moctezuma",
    "contact": "Francisco Chang",
    "country": "Mexico"
}, {
    "company": "Ernst Handel",
    "contact": "Roland Mendel",
    "country": "Austria"
}, {
    "company": "FISSA Fabrica Inter. Salchichas S.A.",
    "contact": "Diego Roel",
    "country": "Spain"
}, {
    "company": "Galería del gastrónomo",
    "contact": "Eduardo Saavedra",
    "country": "Spain"
}, {
    "company": "Island Trading",
    "contact": "Helen Bennett",
    "country": "UK"
}, {
    "company": "Königlich Essen",
    "contact": "Philip Cramer",
    "country": "Germany"
}, {
    "company": "Laughing Bacchus Wine Cellars",
    "contact": "Yoshi Tannamuri",
    "country": "Canada"
}, {
    "company": "Magazzini Alimentari Riuniti",
    "contact": "Giovanni Rovelli",
    "country": "Italy"
}, {
    "company": "North/South",
    "contact": "Simon Crowther",
    "country": "UK"
}, {
    "company": "Paris spécialités",
    "contact": "Marie Bertrand",
    "country": "France"
}, {
    "company": "Rattlesnake Canyon Grocery",
    "contact": "Paula Wilson",
    "country": "USA"
}, {
    "company": "Simons bistro",
    "contact": "Jytte Petersen",
    "country": "Denmark"
}, {
    "company": "The Big Cheese",
    "contact": "Liz Nixon",
    "country": "USA"
}, {
    "company": "Vaffeljernet",
    "contact": "Palle Ibsen",
    "country": "Denmark"
}, {
    "company": "Wolski Zajazd",
    "contact": "Zbyszek Piestrzeniewicz",
    "country": "Poland"
}, {
    "company": "Alfreds Futterkiste",
    "contact": "Maria Anders",
    "country": "Germany"
}, {
    "company": "Berglunds snabbköp",
    "contact": "Christina Berglund",
    "country": "Sweden"
}, {
    "company": "Centro comercial Moctezuma",
    "contact": "Francisco Chang",
    "country": "Mexico"
}, {
    "company": "Ernst Handel",
    "contact": "Roland Mendel",
    "country": "Austria"
}, {
    "company": "Great Lakes Distillery",
    "contact": "Guy Rehorst",
    "country": "USA"
}, {
    "company": "Sint Jacobs Café",
    "contact": "Kobus Le Roux",
    "country": "Netherlands"
}, {
    "company": "Han's Pastry Shop",
    "contact": "Peter Ludwig",
    "country": "USA"
}, {
    "company": "Toms Spezialitäten",
    "contact": "Karin Josephs",
    "country": "Germany"
}, {
    "company": "Victuailles en stock",
    "contact": "Mary Saveley",
    "country": "France"
}, {
    "company": "Queen Co. Ltd.",
    "contact": "Joanna Kowalczyk",
    "country": "Poland"
}, {
    "company": "Vins et alcools Chevalier",
    "contact": "Paul Henriot",
    "country": "France"
}, {
    "company": "Unterstützungsverein",
    "contact": "Jonas Bergulfsen",
    "country": "Sweden"
}, {
    "company": "Ma Maison",
    "contact": "Jean-Guy Lauzon",
    "country": "Canada"
}, {
    "company": "Du monde entier",
    "contact": "Janine Labrune",
    "country": "France"
}, {
    "company": "Bottom-Dollar Markets",
    "contact": "Elizabeth Lincoln",
    "country": "Canada"
}, {
    "company": "Hiltón co.",
    "contact": "Jim Hilton",
    "country": "USA"
}, {
    "company": "Rattlesnake Canyon Grocery",
    "contact": "Paula Wilson",
    "country": "USA"
}, {
    "company": "Split Rail Beer & Ale",
    "contact": "Luke Rodgers",
    "country": "Canada"
}, {
    "company": "The Cracker Box",
    "contact": "Liu Wong",
    "country": "USA"
}, {
    "company": "The Wine Depot",
    "contact": "Michael Holz",
    "country": "Canada"
}, {
    "company": "Wellington Importadora",
    "contact": "Paula Parente",
    "country": "Brazil"
}, {
    "company": "Franchi S.p.A.",
    "contact": "Paolo Accorti",
    "country": "Italy"
}, {
    "company": "Blondel père et fils",
    "contact": "Frédérique Citeaux",
    "country": "France"
}, {
    "company": "Bólido Comidas preparadas",
    "contact": "Martín Sommer",
    "country": "Argentina"
}, {
    "company": "LILA-Supermercado",
    "contact": "Carlos González",
    "country": "Venezuela"
}, {
    "company": "LINO-Delicateses",
    "contact": "Felipe Izquierdo",
    "country": "Portugal"
}, {
    "company": "LILA-Supermercado",
    "contact": "Carlos González",
    "country": "Venezuela"
}, {
    "company": "LINO-Delicateses",
    "contact": "Felipe Izquierdo",
    "country": "Portugal"
}, {
    "company": "Pericles Comidas clásicas",
    "contact": "Guillermo Fernández",
    "country": "Mexico"
}, {
    "company": "B's Beverages",
    "contact": "Victoria Ashworth",
    "country": "UK"
}, {
    "company": "Océano Atlántico Ltda.",
    "contact": "Yvonne Moncada",
    "country": "Argentina"
}, {
    "company": "Antonio Moreno Taquería",
    "contact": "Antonio Moreno",
    "country": "Mexico"
}, {
    "company": "Santé Gourmet",
    "contact": "Jonas Bergulfsen",
    "country": "Sweden"
}, {
    "company": "Familia Arquibaldo",
    "contact": "Aria Cruz",
    "country": "Brazil"
}, {
    "company": "GROSELLA-Restaurante",
    "contact": "Manuel Pereira",
    "country": "Spain"
}, {
    "company": "Simons bistro",
    "contact": "Jytte Petersen",
    "country": "Denmark"
}, {
    "company": "Richter Supermarkt",
    "contact": "Michael Holz",
    "country": "Germany"
}, {
    "company": "Galería del gastrónomo",
    "contact": "Eduardo Saavedra",
    "country": "Spain"
}, {
    "company": "Toms Spezialitäten",
    "contact": "Karin Josephs",
    "country": "Germany"
}, {
    "company": "Vaffeljernet",
    "contact": "Palle Ibsen",
    "country": "Denmark"
}, {
    "company": "HILTON CO",
    "contact": "Jim Hilton",
    "country": "USA"
}, {
    "company": "The Big Cheese",
    "contact": "Liz Nixon",
    "country": "USA"
}, {
    "company": "Island Trading",
    "contact": "Helen Bennett",
    "country": "UK"
}, {
    "company": "Han's Supermarket",
    "contact": "Nancy Krikorian",
    "country": "USA"
}, {
    "company": "Que Delícia",
    "contact": "Bernardo Batista",
    "country": "Brazil"
}, {
    "company": "Ernst Handel",
    "contact": "Roland Mendel",
    "country": "Austria"
}, {
    "company": "La maison d'Asie",
    "contact": "Annette Roulet",
    "country": "France"
}, {
    "company": "Reggiani Caseifici",
    "contact": "Maurizio Moroni",
    "country": "Italy"
}, {
    "company": "LILA-Supermercado",
    "contact": "Carlos González",
    "country": "Venezuela"
}, {
    "company": "Die Wandernde Kuh",
    "contact": "Rita Müller",
    "country": "Germany"
}, {
    "company": "The Big Cheese",
    "contact": "Liz Nixon",
    "country": "USA"
}, {
    "company": "Ernst Handel",
    "contact": "Roland Mendel",
    "country": "Austria"
}, {
    "company": "Wolski Zajazd",
    "contact": "Zbyszek Piestrzeniewicz",
    "country": "Poland"
}, {
    "company": "Laughing Bacchus Wine Cellars",
    "contact": "Yoshi Tannamuri",
    "country": "Canada"
}, {
    "company": "Island Trading",
    "contact": "Helen Bennett",
    "country": "UK"
}, {
    "company": "Familia Arquibaldo",
    "contact": "Aria Cruz",
    "country": "Brazil"
}, {
    "company": "Pericles Comidas clásicas",
    "contact": "Guillermo Fernández",
    "country": "Mexico"
}, {
    "company": "Que Delícia",
    "contact": "Bernardo Batista",
    "country": "Brazil"
}, {
    "company": "La maison d'Asie",
    "contact": "Annette Roulet",
    "country": "France"
}, {
    "company": "Reggiani Caseifici",
    "contact": "Maurizio Moroni",
    "country": "Italy"
}, {
    "company": "Die Wandernde Kuh",
    "contact": "Rita Müller",
    "country": "Brazil"
}, {
    "company": "Bolido Foods",
    "contact": "Carlos Rodriguez",
    "country": "Argentina"
}, {
    "company": "Café au Lait",
    "contact": "Marie Leclerc",
    "country": "France"
}, {
    "company": "Eastern Delights",
    "contact": "Ahmed Hassan",
    "country": "Egypt"
}, {
    "company": "Fresco Groceries",
    "contact": "Luisa Fernandez",
    "country": "Spain"
}, {
    "company": "Gourmet Express",
    "contact": "Sophie Dupont",
    "country": "France"
}, {
    "company": "Harbour Seafood",
    "contact": "John Smith",
    "country": "Canada"
}, {
    "company": "Italiano Trattoria",
    "contact": "Giuseppe Rossi",
    "country": "Italy"
}, {
    "company": "Jasmine Café",
    "contact": "Linh Nguyen",
    "country": "Vietnam"
}, {
    "company": "Kingsley Imports",
    "contact": "Emily Chen",
    "country": "Australia"
}, {
    "company": "La Patisserie",
    "contact": "Julien Bernard",
    "country": "France"
}, {
    "company": "Mundo Latino",
    "contact": "Pedro Morales",
    "country": "Mexico"
}, {
    "company": "Nordic Delights",
    "contact": "Erik Jansen",
    "country": "Norway"
}, {
    "company": "Olive Branch Foods",
    "contact": "Sophia Papadopoulos",
    "country": "Greece"
}, {
    "company": "Pacific Coast Provisions",
    "contact": "Jane Kim",
    "country": "USA"
}, {
    "company": "Quality Meats",
    "contact": "Adam Brown",
    "country": "Canada"
}, {
    "company": "Roma Enoteca",
    "contact": "Giovanni Bianchi",
    "country": "Italy"
}, {
    "company": "Safari Delicatessen",
    "contact": "Sara Mbeki",
    "country": "Kenya"
}, {
    "company": "Taj Mahal Foods",
    "contact": "Raj Patel",
    "country": "India"
}, {
    "company": "Union Jack Foods",
    "contact": "Alice Thompson",
    "country": "UK"
}, {
    "company": "Viking Pantry",
    "contact": "Thor Olafsson",
    "country": "Iceland"
}, {
    "company": "Wild West Meats",
    "contact": "Bill Jackson",
    "country": "USA"
}, {
    "company": "Xanadu Sweets",
    "contact": "Lily Wang",
    "country": "China"
}, {
    "company": "Yucatan Spices",
    "contact": "Ana Gutierrez",
    "country": "Mexico"
}, {
    "company": "Zesty Flavors",
    "contact": "Michelle Lee",
    "country": "Singapore"
}, {
    "company": "Alpino's Delicatessen",
    "contact": "Luigi Moretti",
    "country": "Italy"
}, {
    "company": "Bellissimo Bistro",
    "contact": "Antonio De Luca",
    "country": "Canada"
}, {
    "company": "Casa del Queso",
    "contact": "María López",
    "country": "Spain"
}, {
    "company": "Deli Delights",
    "contact": "Hannah Roberts",
    "country": "Australia"
}, {
    "company": "Euro Market",
    "contact": "Stefan Mueller",
    "country": "Germany"
}, {
    "company": "French Riviera Gourmet",
    "contact": "Claire Dubois",
    "country": "France"
}, {
    "company": "Gusto Italiano",
    "contact": "Mario Rossi",
    "country": "Italy"
}, {
    "company": "Himalayan Spices",
    "contact": "Ravi Gupta",
    "country": "Nepal"
}, {
    "company": "Island Flavors",
    "contact": "Leilani Koa",
    "country": "Hawaii"
}, {
    "company": "Jolly Jams",
    "contact": "Emily Smith",
    "country": "UK"
}, {
    "company": "Kaiser Bakery",
    "contact": "Heinrich Müller",
    "country": "Germany"
}, {
    "company": "Lucky Lotus",
    "contact": "Jasmine Wu",
    "country": "China"
}, {
    "company": "Mamma Mia's Kitchen",
    "contact": "Giovanni Ferrari",
    "country": "Italy"
}, {
    "company": "Napa Valley Vineyards",
    "contact": "Olivia Davis",
    "country": "USA"
}, {
    "company": "Olive Tree Bistro",
    "contact": "Nikos Papadopoulos",
    "country": "Greece"
}, {
    "company": "Polar Bear Ice Cream",
    "contact": "Sven Eriksson",
    "country": "Sweden"
}, {
    "company": "Queen's Cupcake Castle",
    "contact": "Victoria Windsor",
    "country": "UK"
}, {
    "company": "Red Dragon Sushi",
    "contact": "Yuki Tanaka",
    "country": "Japan"
}, {
    "company": "Sabor Tropical",
    "contact": "Maria Santos",
    "country": "Brazil"
}, {
    "company": "Thai Orchid Cuisine",
    "contact": "Somchai Noppakun",
    "country": "Thailand"
}, {
    "company": "Uptown Deli",
    "contact": "Rachel Cohen",
    "country": "USA"
}, {
    "company": "Venetian Delights",
    "contact": "Giorgio Conte",
    "country": "Italy"
}, {
    "company": "West Coast Wines",
    "contact": "Michael Nguyen",
    "country": "USA"
}, {
    "company": "Xanadu Sweets",
    "contact": "Lily Wang",
    "country": "China"
}, {
    "company": "Yucatan Spices",
    "contact": "Ana Gutierrez",
    "country": "Mexico"
}, {
    "company": "Zesty Flavors",
    "contact": "Michelle Lee",
    "country": "Singapore"
}, {
    "company": "Aloha Grill",
    "contact": "Kai Kalani",
    "country": "Hawaii"
}, {
    "company": "Bavarian Delicatessen",
    "contact": "Hans Schmidt",
    "country": "Germany"
}, {
    "company": "Café de la Luna",
    "contact": "Alejandro Castillo",
    "country": "Argentina"
}, {
    "company": "Delightful Desserts",
    "contact": "Chloe Baker",
    "country": "Australia"
}, {
    "company": "El Mariachi",
    "contact": "Miguel Hernandez",
    "country": "Mexico"
}, {
    "company": "Fiesta Foods",
    "contact": "Diego Sánchez",
    "country": "Spain"
}, {
    "company": "Ginger Spice",
    "contact": "Lin Hui",
    "country": "China"
}, {
    "company": "Happy Harvest",
    "contact": "Emma Johnson",
    "country": "Canada"
}, {
    "company": "Italiano Trattoria",
    "contact": "Giuseppe Rossi",
    "country": "Italy"
}, {
    "company": "Jade Palace",
    "contact": "Li Wei",
    "country": "China"
}, {
    "company": "Kabul Delights",
    "contact": "Mohammad Khan",
    "country": "Afghanistan"
}]

